jupyterlab_browser_ai/__init__.py
jupyterlab_browser_ai/_version.py
jupyterlab_browser_ai-0.4.2.data/data/share/jupyter/labextensions/jupyterlab-browser-ai/package.json
jupyterlab_browser_ai-0.4.2.data/data/share/jupyter/labextensions/jupyterlab-browser-ai/schemas/jupyterlab-browser-ai/package.json.orig
jupyterlab_browser_ai-0.4.2.data/data/share/jupyter/labextensions/jupyterlab-browser-ai/schemas/jupyterlab-browser-ai/plugin.json
jupyterlab_browser_ai-0.4.2.data/data/share/jupyter/labextensions/jupyterlab-browser-ai/static/143.86bc3e43af801c8133a6.js
jupyterlab_browser_ai-0.4.2.data/data/share/jupyter/labextensions/jupyterlab-browser-ai/static/190.972be577205a74543e93.js
jupyterlab_browser_ai-0.4.2.data/data/share/jupyter/labextensions/jupyterlab-browser-ai/static/509.08ad9dbf444cfe01d52e.js
jupyterlab_browser_ai-0.4.2.data/data/share/jupyter/labextensions/jupyterlab-browser-ai/static/635.da82751eec1f169393a7.js
jupyterlab_browser_ai-0.4.2.data/data/share/jupyter/labextensions/jupyterlab-browser-ai/static/728.8a6b2b98cc1cde1ed0fb.js
jupyterlab_browser_ai-0.4.2.data/data/share/jupyter/labextensions/jupyterlab-browser-ai/static/808.e88343788a05781cdf07.js
jupyterlab_browser_ai-0.4.2.data/data/share/jupyter/labextensions/jupyterlab-browser-ai/static/remoteEntry.084f49118a0dee3496f6.js
jupyterlab_browser_ai-0.4.2.data/data/share/jupyter/labextensions/jupyterlab-browser-ai/static/style.js
jupyterlab_browser_ai-0.4.2.data/data/share/jupyter/labextensions/jupyterlab-browser-ai/static/third-party-licenses.json
jupyterlab_browser_ai-0.4.2.data/data/share/jupyter/labextensions/jupyterlab-browser-ai/install.json
jupyterlab_browser_ai-0.4.2.dist-info/METADATA
jupyterlab_browser_ai-0.4.2.dist-info/WHEEL
jupyterlab_browser_ai-0.4.2.dist-info/licenses/LICENSE
jupyterlab_browser_ai-0.4.2.dist-info/RECORD
