Metadata-Version: 2.4
Name: jupyterlab_browser_ai
Version: 0.4.2
Summary: In-browser AI in JupyterLab and Jupyter Notebook
Project-URL: Homepage, https://github.com/jtpio/jupyterlab-browser-ai
Project-URL: Bug Tracker, https://github.com/jtpio/jupyterlab-browser-ai/issues
Project-URL: Repository, https://github.com/jtpio/jupyterlab-browser-ai.git
Author: Jeremy Tuloup
License: BSD 3-Clause License
License-File: LICENSE
Keywords: jupyter,jupyterlab,jupyterlab-extension
Classifier: Framework :: Jupyter
Classifier: Framework :: Jupyter :: JupyterLab
Classifier: Framework :: Jupyter :: JupyterLab :: 4
Classifier: Framework :: Jupyter :: JupyterLab :: Extensions
Classifier: Framework :: Jupyter :: JupyterLab :: Extensions :: Prebuilt
Classifier: License :: OSI Approved :: BSD License
Classifier: Programming Language :: Python
Classifier: Programming Language :: Python :: 3
Classifier: Programming Language :: Python :: 3.9
Classifier: Programming Language :: Python :: 3.10
Classifier: Programming Language :: Python :: 3.11
Classifier: Programming Language :: Python :: 3.12
Classifier: Programming Language :: Python :: 3.13
Requires-Python: >=3.9
Requires-Dist: jupyterlite-ai>=0.9.0a3
